libcoveofds/__init__.py
libcoveofds/additionalfields.py
libcoveofds/cli.py
libcoveofds/geojson.py
libcoveofds/jsonschemavalidate.py
libcoveofds/python_validate.py
libcoveofds/schema.py
libcoveofds/data/schema-0-3-0-network-only.json
libcoveofds/data/schema-0-3-0.json
libcoveofds-0.9.0.dist-info/LICENSE
libcoveofds-0.9.0.dist-info/METADATA
libcoveofds-0.9.0.dist-info/WHEEL
libcoveofds-0.9.0.dist-info/entry_points.txt
libcoveofds-0.9.0.dist-info/top_level.txt
libcoveofds-0.9.0.dist-info/RECORD
