Metadata-Version: 2.1
Name: libcoveofds
Version: 0.9.0
Summary: A data review library
Home-page: https://github.com/Open-Telecoms-Data/lib-cove-ofds
Author: Open Data Services
Author-email: code@opendataservices.coop
License: UNKNOWN
Project-URL: Documentation, https://libcoveofds.readthedocs.io/en/latest/
Project-URL: Issues, https://github.com/Open-Telecoms-Data/lib-cove-ofds/issues
Project-URL: Source, https://github.com/Open-Telecoms-Data/lib-cove-ofds
Platform: UNKNOWN
Classifier: License :: OSI Approved :: GNU Affero General Public License v3 or later (AGPLv3+)
Requires-Python: >=3.8
Requires-Dist: json-merge-patch
Requires-Dist: jsonschema
Requires-Dist: libcove2
Requires-Dist: rfc3987
Provides-Extra: dev
Requires-Dist: Sphinx ; extra == 'dev'
Requires-Dist: black (==22.3.0) ; extra == 'dev'
Requires-Dist: flake8 ; extra == 'dev'
Requires-Dist: isort ; extra == 'dev'
Requires-Dist: mypy ; extra == 'dev'
Requires-Dist: pytest ; extra == 'dev'
